moss_mcp_server/MossAPIClient.py
moss_mcp_server/SecurityUtil.py
moss_mcp_server/__init__.py
moss_mcp_server/my_ex.py
moss_mcp_server/server.py
moss_mcp_server-0.1.3.dist-info/METADATA
moss_mcp_server-0.1.3.dist-info/WHEEL
moss_mcp_server-0.1.3.dist-info/entry_points.txt
moss_mcp_server-0.1.3.dist-info/top_level.txt
moss_mcp_server-0.1.3.dist-info/RECORD
