Metadata-Version: 2.4
Name: moss_mcp_server
Version: 0.1.3
Summary: Add your description here
Home-page: https://github.com/alashanprivate/moss_mcp_server
Author: fenda
Author-email: alashanprivate@163.com
Requires-Python: >=3.6
Requires-Dist: cryptography>=45.0.1
Requires-Dist: httpx>=0.28.1
Requires-Dist: mcp[cli]>=1.9.0
Requires-Dist: requests>=2.32.3
Dynamic: author
Dynamic: author-email
Dynamic: home-page
Dynamic: requires-python
